asgify/__init__.py
asgify/app.py
asgify/context.py
asgify/errors.py
asgify/py.typed
asgify/status.py
asgify-0.3.0.dist-info/licenses/LICENSE
asgify-0.3.0.dist-info/METADATA
asgify-0.3.0.dist-info/WHEEL
asgify-0.3.0.dist-info/top_level.txt
asgify-0.3.0.dist-info/RECORD
