Metadata-Version: 2.4
Name: asgify
Version: 0.3.0
Summary: Opinionless ASGI Framework 🙌
Project-URL: Homepage, https://github.com/aprilahijriyan/asgify
Project-URL: Repository, https://github.com/aprilahijriyan/asgify
Project-URL: Documentation, https://github.com/aprilahijriyan/asgify#readme
Classifier: Programming Language :: Python :: 3
Classifier: Framework :: AsyncIO
Classifier: License :: OSI Approved :: MIT License
Classifier: Operating System :: OS Independent
Classifier: Intended Audience :: Developers
Classifier: Topic :: Software Development :: Libraries :: Application Frameworks
Classifier: Development Status :: 4 - Beta
Requires-Python: >=3.9
License-File: LICENSE
Requires-Dist: asgiref>=3.9.0
Requires-Dist: fast-query-parsers>=1.0.3
Requires-Dist: multidict>=6.6.3
Dynamic: license-file
